deepfastmlu/__init__.py
deepfastmlu/extra/__init__.py
deepfastmlu/extra/data_helpers.py
deepfastmlu/extra/plot_helpers.py
deepfastmlu/feature_select/AdaptiveVarianceThreshold.py
deepfastmlu/feature_select/ChainedFS.py
deepfastmlu/feature_select/RankAggregatedFS.py
deepfastmlu/feature_select/__init__.py
deepfastmlu/model_search/PCCDNAS.py
deepfastmlu/model_search/__init__.py
deepfastmlu-0.1.dist-info/LICENSE
deepfastmlu-0.1.dist-info/METADATA
deepfastmlu-0.1.dist-info/WHEEL
deepfastmlu-0.1.dist-info/top_level.txt
deepfastmlu-0.1.dist-info/RECORD
